stookwijzer/__init__.py
stookwijzer/const.py
stookwijzer/example.py
stookwijzer/stookwijzerapi.py
stookwijzer-1.6.0.dist-info/LICENSE
stookwijzer-1.6.0.dist-info/METADATA
stookwijzer-1.6.0.dist-info/WHEEL
stookwijzer-1.6.0.dist-info/top_level.txt
stookwijzer-1.6.0.dist-info/RECORD
